triangle_mesh_io/__init__.py
triangle_mesh_io/convert.py
triangle_mesh_io/obj.py
triangle_mesh_io/off.py
triangle_mesh_io/stl.py
triangle_mesh_io/version.py
triangle_mesh_io/mesh/__init__.py
triangle_mesh_io/mesh/artifacts.py
triangle_mesh_io/mesh/cluster.py
triangle_mesh_io/mesh/graph.py
triangle_mesh_io/mesh/normal.py
triangle_mesh_io/tests/resources/gridfinity_cup_modules_x1-y1-z5.stl
triangle_mesh_io/tests/resources/openucci-rim-disk.obj
triangle_mesh_io/tests/resources/openucci-rim-disk.off
triangle_mesh_io/tests/resources/optical_mirror.obj
triangle_mesh_io/tests/resources/utah_teapot.stl
triangle_mesh_io-0.1.3.dist-info/licenses/LICENSE
triangle_mesh_io-0.1.3.dist-info/METADATA
triangle_mesh_io-0.1.3.dist-info/WHEEL
triangle_mesh_io-0.1.3.dist-info/entry_points.txt
triangle_mesh_io-0.1.3.dist-info/top_level.txt
triangle_mesh_io-0.1.3.dist-info/RECORD
