Metadata-Version: 2.4
Name: triangle_mesh_io
Version: 0.1.3
Summary: Load and dump triangle-meshes from and to OBJ, OFF, and STL.
Home-page: https://github.com/cherenkov-plenoscope/triangle_mesh_io
Author: Sebastian Achim Mueller
Author-email: sebastian-achim.mueller@mpi-hd.mpg.de
Classifier: Programming Language :: Python :: 3
Classifier: License :: OSI Approved :: MIT License
Classifier: Operating System :: OS Independent
Classifier: Natural Language :: English
Classifier: Topic :: File Formats
Classifier: Topic :: Scientific/Engineering
Classifier: Topic :: Scientific/Engineering :: Visualization
Classifier: Topic :: Scientific/Engineering :: Physics
Classifier: Topic :: Games/Entertainment
Classifier: Topic :: Multimedia :: Graphics
Classifier: Topic :: Multimedia :: Graphics :: 3D Modeling
Classifier: Topic :: Multimedia :: Graphics :: Editors
License-File: LICENSE
Requires-Dist: numpy
Requires-Dist: scikit-learn
Dynamic: author
Dynamic: author-email
Dynamic: classifier
Dynamic: description
Dynamic: description-content-type
Dynamic: home-page
Dynamic: license-file
Dynamic: requires-dist
Dynamic: summary
